ConnectomeMatch.py
ConnectomeMatch-0.0.8.dist-info/LICENSE
ConnectomeMatch-0.0.8.dist-info/METADATA
ConnectomeMatch-0.0.8.dist-info/WHEEL
ConnectomeMatch-0.0.8.dist-info/top_level.txt
ConnectomeMatch-0.0.8.dist-info/RECORD
