Metadata-Version: 2.1
Name: ConnectomeMatch
Version: 0.0.8
Summary: Inexact graph matching and significance testing for groups of graphs
Home-page: https://github.com/u01ai11/ConnectomeMatch
Author: Alexander Anwyl-Irvine & Edwin Dalmaijer
Author-email: anwyl.irvine@gmail.com
License: UNKNOWN
Project-URL: Bug Tracker, https://github.com/u01ai11/ConnectomeMatch/issues
Platform: UNKNOWN
Classifier: Programming Language :: Python :: 3
Classifier: License :: OSI Approved :: MIT License
Classifier: Operating System :: OS Independent
Requires-Python: >=3.6
License-File: LICENSE
Requires-Dist: scipy
Requires-Dist: numpy
Requires-Dist: joblib
Requires-Dist: enum34 ; python_version < "3.4"
